{
"meta":{"test_sets":[],"test_metrics":[],"learn_metrics":[{"best_value":"Min","name":"RMSE"}],"launch_mode":"Train","parameters":"","iteration_count":100,"learn_sets":["learn"],"name":"experiment"},
"iterations":[
{"learn":[14.84063055],"iteration":0,"passed_time":0.0005728219025,"remaining_time":0.05670936835},
{"learn":[14.0277146],"iteration":1,"passed_time":0.0010907699,"remaining_time":0.0534477251},
{"learn":[13.28168108],"iteration":2,"passed_time":0.001520136332,"remaining_time":0.04915107473},
{"learn":[12.67295736],"iteration":3,"passed_time":0.001952461038,"remaining_time":0.04685906491},
{"learn":[12.13118282],"iteration":4,"passed_time":0.002410285235,"remaining_time":0.04579541947},
{"learn":[11.64284615],"iteration":5,"passed_time":0.002914233512,"remaining_time":0.04565632503},
{"learn":[11.17583451],"iteration":6,"passed_time":0.003373474348,"remaining_time":0.04481901634},
{"learn":[10.70698042],"iteration":7,"passed_time":0.003785341129,"remaining_time":0.04353142298},
{"learn":[10.30261074],"iteration":8,"passed_time":0.004214082573,"remaining_time":0.04260905713},
{"learn":[9.897928797],"iteration":9,"passed_time":0.004857236406,"remaining_time":0.04371512765},
{"learn":[9.43818595],"iteration":10,"passed_time":0.005286727835,"remaining_time":0.0427744343},
{"learn":[9.067087678],"iteration":11,"passed_time":0.005673220123,"remaining_time":0.04160361423},
{"learn":[8.769647814],"iteration":12,"passed_time":0.00606171237,"remaining_time":0.04056684432},
{"learn":[8.494260327],"iteration":13,"passed_time":0.006583910283,"remaining_time":0.04044402031},
{"learn":[8.18170444],"iteration":14,"passed_time":0.007117357971,"remaining_time":0.04033169517},
{"learn":[7.872819124],"iteration":15,"passed_time":0.00763959755,"remaining_time":0.04010788714},
{"learn":[7.637017332],"iteration":16,"passed_time":0.008017506675,"remaining_time":0.0391442973},
{"learn":[7.415872705],"iteration":17,"passed_time":0.00841162381,"remaining_time":0.03831961958},
{"learn":[7.161020449],"iteration":18,"passed_time":0.008906030611,"remaining_time":0.03796781471},
{"learn":[6.971236341],"iteration":19,"passed_time":0.009319855686,"remaining_time":0.03727942274},
{"learn":[6.841615556],"iteration":20,"passed_time":0.009735680722,"remaining_time":0.03662470367},
{"learn":[6.687931434],"iteration":21,"passed_time":0.01027762824,"remaining_time":0.03643886376},
{"learn":[6.508058838],"iteration":22,"passed_time":0.01082157572,"remaining_time":0.03622875349},
{"learn":[6.348045518],"iteration":23,"passed_time":0.01128019157,"remaining_time":0.03572060663},
{"learn":[6.190854657],"iteration":24,"passed_time":0.01175893201,"remaining_time":0.03527679604},
{"learn":[6.083848414],"iteration":25,"passed_time":0.01230458779,"remaining_time":0.03502074987},
{"learn":[5.948861607],"iteration":26,"passed_time":0.0128820346,"remaining_time":0.03482920466},
{"learn":[5.820594273],"iteration":27,"passed_time":0.0133230258,"remaining_time":0.0342592092},
{"learn":[5.718358733],"iteration":28,"passed_time":0.0137723085,"remaining_time":0.03371841047},
{"learn":[5.62831756],"iteration":29,"passed_time":0.01423642424,"remaining_time":0.03321832323},
{"learn":[5.501668539],"iteration":30,"passed_time":0.01477541349,"remaining_time":0.03288721066},
{"learn":[5.404367962],"iteration":31,"passed_time":0.01522819612,"remaining_time":0.03235991675},
{"learn":[5.312889065],"iteration":32,"passed_time":0.01569589512,"remaining_time":0.03186742342},
{"learn":[5.220401854],"iteration":33,"passed_time":0.01607930413,"remaining_time":0.03121276685},
{"learn":[5.130160358],"iteration":34,"passed_time":0.01659529384,"remaining_time":0.03081983141},
{"learn":[5.056241699],"iteration":35,"passed_time":0.0170098689,"remaining_time":0.03023976693},
{"learn":[4.971821431],"iteration":36,"passed_time":0.01746485982,"remaining_time":0.02973746401},
{"learn":[4.90630594],"iteration":37,"passed_time":0.01790493437,"remaining_time":0.02921331397},
{"learn":[4.847558899],"iteration":38,"passed_time":0.01835946696,"remaining_time":0.02871608935},
{"learn":[4.795388439],"iteration":39,"passed_time":0.01887258173,"remaining_time":0.02830887259},
{"learn":[4.763423781],"iteration":40,"passed_time":0.01933386419,"remaining_time":0.02782190212},
{"learn":[4.718909606],"iteration":41,"passed_time":0.01976110566,"remaining_time":0.02728914591},
{"learn":[4.660496339],"iteration":42,"passed_time":0.02019397202,"remaining_time":0.02676875361},
{"learn":[4.619083415],"iteration":43,"passed_time":0.02073383625,"remaining_time":0.02638851886},
{"learn":[4.578792627],"iteration":44,"passed_time":0.02119741033,"remaining_time":0.02590794596},
{"learn":[4.53420217],"iteration":45,"passed_time":0.0216018606,"remaining_time":0.02535870592},
{"learn":[4.480755407],"iteration":46,"passed_time":0.02201993559,"remaining_time":0.02483099119},
{"learn":[4.440459443],"iteration":47,"passed_time":0.02252959208,"remaining_time":0.02440705809},
{"learn":[4.399489675],"iteration":48,"passed_time":0.02314187153,"remaining_time":0.02408643772},
{"learn":[4.351777663],"iteration":49,"passed_time":0.02364181989,"remaining_time":0.02364181989},
{"learn":[4.322290972],"iteration":50,"passed_time":0.02416418446,"remaining_time":0.02321656939},
{"learn":[4.294233013],"iteration":51,"passed_time":0.02475483934,"remaining_time":0.02285062093},
{"learn":[4.275623532],"iteration":52,"passed_time":0.02518737238,"remaining_time":0.02233597173},
{"learn":[4.237862852],"iteration":53,"passed_time":0.02562294702,"remaining_time":0.02182695487},
{"learn":[4.20766476],"iteration":54,"passed_time":0.02605014683,"remaining_time":0.0213137565},
{"learn":[4.188319833],"iteration":55,"passed_time":0.02671180029,"remaining_time":0.02098784309},
{"learn":[4.150006672],"iteration":56,"passed_time":0.02715374981,"remaining_time":0.02048440775},
{"learn":[4.109226526],"iteration":57,"passed_time":0.02761578225,"remaining_time":0.01999763542},
{"learn":[4.077151393],"iteration":58,"passed_time":0.02803627386,"remaining_time":0.01948283438},
{"learn":[4.043789762],"iteration":59,"passed_time":0.0286041792,"remaining_time":0.0190694528},
{"learn":[4.035036878],"iteration":60,"passed_time":0.02892279784,"remaining_time":0.01849162485},
{"learn":[4.013853126],"iteration":61,"passed_time":0.02932833141,"remaining_time":0.01797542893},
{"learn":[3.979587038],"iteration":62,"passed_time":0.02986402905,"remaining_time":0.01753919167},
{"learn":[3.950449041],"iteration":63,"passed_time":0.03039076854,"remaining_time":0.01709480731},
{"learn":[3.941048557],"iteration":64,"passed_time":0.0307971771,"remaining_time":0.01658309536},
{"learn":[3.919502044],"iteration":65,"passed_time":0.03125375132,"remaining_time":0.01610041735},
{"learn":[3.908419086],"iteration":66,"passed_time":0.03174807479,"remaining_time":0.01563711146},
{"learn":[3.883974731],"iteration":67,"passed_time":0.03228502241,"remaining_time":0.01519295172},
{"learn":[3.862579573],"iteration":68,"passed_time":0.03283671973,"remaining_time":0.01475272916},
{"learn":[3.849836895],"iteration":69,"passed_time":0.03325679468,"remaining_time":0.01425291201},
{"learn":[3.824998864],"iteration":70,"passed_time":0.03378224253,"remaining_time":0.01379838075},
{"learn":[3.791315502],"iteration":71,"passed_time":0.03421477557,"remaining_time":0.01330574605},
{"learn":[3.758805858],"iteration":72,"passed_time":0.03472218211,"remaining_time":0.01284245092},
{"learn":[3.739757196],"iteration":73,"passed_time":0.035195131,"remaining_time":0.01236585684},
{"learn":[3.727492189],"iteration":74,"passed_time":0.03562574741,"remaining_time":0.01187524914},
{"learn":[3.706251604],"iteration":75,"passed_time":0.03635369122,"remaining_time":0.01148011302},
{"learn":[3.685860196],"iteration":76,"passed_time":0.03694576274,"remaining_time":0.01103574731},
{"learn":[3.663779561],"iteration":77,"passed_time":0.03736058779,"remaining_time":0.01053760168},
{"learn":[3.648059878],"iteration":78,"passed_time":0.03786428607,"remaining_time":0.01006518997},
{"learn":[3.643276906],"iteration":79,"passed_time":0.03843298306,"remaining_time":0.009608245765},
{"learn":[3.638022193],"iteration":80,"passed_time":0.03913471905,"remaining_time":0.009179748914},
{"learn":[3.625433746],"iteration":81,"passed_time":0.03971062423,"remaining_time":0.008716966294},
{"learn":[3.596253585],"iteration":82,"passed_time":0.04029369593,"remaining_time":0.008252925672},
{"learn":[3.571081695],"iteration":83,"passed_time":0.04081714381,"remaining_time":0.00777469406},
{"learn":[3.56195045],"iteration":84,"passed_time":0.0413859658,"remaining_time":0.007303405729},
{"learn":[3.518241793],"iteration":85,"passed_time":0.04198007894,"remaining_time":0.006833966339},
{"learn":[3.494336727],"iteration":86,"passed_time":0.04253623451,"remaining_time":0.006355989065},
{"learn":[3.478022077],"iteration":87,"passed_time":0.04356467232,"remaining_time":0.005940637135},
{"learn":[3.450668514],"iteration":88,"passed_time":0.04423415896,"remaining_time":0.005467143242},
{"learn":[3.419074933],"iteration":89,"passed_time":0.04470935781,"remaining_time":0.004967706423},
{"learn":[3.376901598],"iteration":90,"passed_time":0.04519526478,"remaining_time":0.004469861352},
{"learn":[3.365852239],"iteration":91,"passed_time":0.04562563119,"remaining_time":0.003967446191},
{"learn":[3.34189864],"iteration":92,"passed_time":0.04607178896,"remaining_time":0.003467769061},
{"learn":[3.320205229],"iteration":93,"passed_time":0.04660227837,"remaining_time":0.002974613513},
{"learn":[3.307646434],"iteration":94,"passed_time":0.04703351977,"remaining_time":0.002475448409},
{"learn":[3.304337773],"iteration":95,"passed_time":0.04749751051,"remaining_time":0.001979062938},
{"learn":[3.28404604],"iteration":96,"passed_time":0.04790654401,"remaining_time":0.001481645691},
{"learn":[3.262609827],"iteration":97,"passed_time":0.0484816992,"remaining_time":0.0009894224326},
{"learn":[3.252134778],"iteration":98,"passed_time":0.04902598001,"remaining_time":0.0004952119192},
{"learn":[3.245174796],"iteration":99,"passed_time":0.04953192824,"remaining_time":0}
]}